osc_transformer_presteps-0.1.9.dist-info/METADATA
osc_transformer_presteps-0.1.9.dist-info/WHEEL
osc_transformer_presteps-0.1.9.dist-info/entry_points.txt
osc_transformer_presteps-0.1.9.dist-info/licenses/LICENSE.txt
osc_transformer_presteps/__init__.py
osc_transformer_presteps/cli.py
osc_transformer_presteps/content_extraction/__init__.py
osc_transformer_presteps/content_extraction/extraction_factory.py
osc_transformer_presteps/content_extraction/extractors/__init__.py
osc_transformer_presteps/content_extraction/extractors/base_extractor.py
osc_transformer_presteps/content_extraction/extractors/pdf_text_extractor.py
osc_transformer_presteps/folderizer/__init__.py
osc_transformer_presteps/folderizer/folderizer_main.py
osc_transformer_presteps/kpi_detection_dataset_curation/__init__.py
osc_transformer_presteps/kpi_detection_dataset_curation/kpi_curator_function/__init__.py
osc_transformer_presteps/kpi_detection_dataset_curation/kpi_curator_function/kpi_curation.py
osc_transformer_presteps/kpi_detection_dataset_curation/kpi_curator_function/kpi_data_processing.py
osc_transformer_presteps/kpi_detection_dataset_curation/kpi_curator_function/kpi_example_creation.py
osc_transformer_presteps/kpi_detection_dataset_curation/kpi_curator_function/kpi_utils.py
osc_transformer_presteps/kpi_detection_dataset_curation/kpi_curator_main.py
osc_transformer_presteps/relevance_detection_dataset_curation/__init__.py
osc_transformer_presteps/relevance_detection_dataset_curation/curator.py
osc_transformer_presteps/run_local_extraction.py
osc_transformer_presteps/run_local_folder_structure_maker.py
osc_transformer_presteps/run_local_kpi_curation.py
osc_transformer_presteps/run_local_relevance_curation.py
osc_transformer_presteps/settings.py
osc_transformer_presteps/utils.py
osc_transformer_presteps-0.1.9.dist-info/RECORD
