Metadata-Version: 2.1
Name: osc-transformer-presteps
Version: 0.1.9
Summary: OS-Climate Data Extraction Tool
Author-Email: David Besslich <90916810+DaBeIDS@users.noreply.github.com>
License:                                  Apache License
Classifier: Intended Audience :: Developers
Classifier: Intended Audience :: Science/Research
Classifier: License :: OSI Approved :: Apache Software License
Classifier: Operating System :: MacOS
Classifier: Operating System :: Microsoft :: Windows
Classifier: Operating System :: Unix
Classifier: Programming Language :: Python
Classifier: Programming Language :: Python :: 3
Classifier: Programming Language :: Python :: 3 :: Only
Classifier: Programming Language :: Python :: 3.11
Classifier: Programming Language :: Python :: 3.10
Classifier: Topic :: Office/Business :: Financial
Classifier: Topic :: Scientific/Engineering
Classifier: Topic :: Software Development
Project-URL: Homepage, https://github.com/os-climate/osc-transformer-presteps
Project-URL: Repository, https://github.com/os-climate/osc-transformer-presteps
Project-URL: Downloads, https://github.com/os-climate/osc-transformer-presteps/releases
Project-URL: Bug Tracker, https://github.com/os-climate/osc-transformer-presteps/issues
Project-URL: Documentation, https://github.com/os-climate/osc-transformer-presteps/tree/main/docs
Project-URL: Source Code, https://github.com/os-climate/osc-transformer-presteps
Requires-Python: <3.12,>=3.10
Requires-Dist: pdfminer>=20191125
Requires-Dist: pypdf>=4.0.0
Requires-Dist: numpy>=1.26.3
Requires-Dist: fastapi>=0.109.0
Requires-Dist: uvicorn>=0.27.0.post1
Requires-Dist: python-multipart>=0.0.6
Requires-Dist: streamlit>=1.12.0
Requires-Dist: altair<5
Requires-Dist: types-requests>=2.31.0.20240218
Requires-Dist: pydantic>=2.6.3
Requires-Dist: typer>=0.12.3
Requires-Dist: openpyxl>=3.1.4
Requires-Dist: scikit-learn>=1.5.2
Requires-Dist: rapidfuzz>=3.10.1
Requires-Dist: Levenshtein>=0.26.1
Provides-Extra: dev
Requires-Dist: pylint; extra == "dev"
Requires-Dist: toml; extra == "dev"
Requires-Dist: yapf; extra == "dev"
Requires-Dist: pdm; extra == "dev"
Requires-Dist: tox; extra == "dev"
Requires-Dist: tox-pdm; extra == "dev"
Provides-Extra: test
Requires-Dist: pdm[pytest]; extra == "test"
Requires-Dist: pytest; extra == "test"
Requires-Dist: pytest-cov; extra == "test"
Requires-Dist: pytest-html; extra == "test"
